{
  "code": 200,
  "msg": "Get StoreList Succeeded!",
  "data": {
    "carouselList": [
      {
        "carouselId": 2,
        "carouselName": "竹林香米线",
        "carouselImgUrl": "uploadFile/006fVSiZgy1fremmk8mmmj30u00twq8c.jpg",
        "publicMsg": "这是一碗蓝朋友剥好的小龙虾"
      },
      {
        "carouselId": 3,
        "carouselName": "干锅牛蛙",
        "carouselImgUrl": "uploadFile/006fVSiZgy1fsp0pmgy9sj30u00u0jza.jpg",
        "publicMsg": "这是一碗蓝朋友剥好的小龙虾"
      },
      {
        "carouselId": 4,
        "carouselName": "黄焖鸡米饭",
        "carouselImgUrl": "uploadFile/006fVSiZgy1fssio2es4dj30u00u0n34.jpg",
        "publicMsg": "这是一碗蓝朋友剥好的小龙虾"
      }
    ]
  }
}